model_one/__init__.py
model_one/cli.py
model_one/resource.py
tests/__init__.py
tests/functional/__init__.py
tests/functional/test_model_one.py
model_one-0.1.14.dist-info/METADATA
model_one-0.1.14.dist-info/WHEEL
model_one-0.1.14.dist-info/top_level.txt
model_one-0.1.14.dist-info/RECORD
