Metadata-Version: 2.1
Name: model-one
Version: 0.1.14
Summary: beyondml
Home-page: https://github.com/beyondml/model-one-py
Download-URL: https://pypi.org/project/beyond.ml/
Author: BeyondML
Author-email: drewxa@beyond-ml.ai
License: MIT
Keywords: beyondml,model-one,gpt-3,nlp
Requires-Dist: pandas (>1.4)
Requires-Dist: requests (>2.10)
Requires-Dist: sklearn
